jaziw/__init__.py
jaziw/normalize.py
jaziw/sentenize.py
jaziw/substring.py
jaziw/tokenize.py
jaziw-0.0.2.dist-info/LICENSE
jaziw-0.0.2.dist-info/METADATA
jaziw-0.0.2.dist-info/WHEEL
jaziw-0.0.2.dist-info/top_level.txt
jaziw-0.0.2.dist-info/RECORD
