Metadata-Version: 2.1
Name: jaziw
Version: 0.0.2
Summary: Special opportunities for the Karakalpak language
Author: Turdıbek Jumabaev
Author-email: <turdibekjumabaev05@gmail.com>
Keywords: karakalpak,language,python
Classifier: Development Status :: 1 - Planning
Classifier: Intended Audience :: Developers
Classifier: Programming Language :: Python :: 3
License-File: LICENSE
